odoo10_addon_l10n_nl_account_tax_unece-10.0.1.0.0-py2.7-nspkg.pth
odoo/addons/l10n_nl_account_tax_unece/README.rst
odoo/addons/l10n_nl_account_tax_unece/__init__.py
odoo/addons/l10n_nl_account_tax_unece/__manifest__.py
odoo/addons/l10n_nl_account_tax_unece/post_install.py
odoo/addons/l10n_nl_account_tax_unece/data/account_tax_template.xml
odoo/addons/l10n_nl_account_tax_unece/models/__init__.py
odoo/addons/l10n_nl_account_tax_unece/models/res_company.py
odoo/addons/l10n_nl_account_tax_unece/static/description/icon.png
odoo/addons/l10n_nl_account_tax_unece/tests/__init__.py
odoo/addons/l10n_nl_account_tax_unece/tests/test_nl_account_tax_unece.py
odoo10_addon_l10n_nl_account_tax_unece-10.0.1.0.0.dist-info/DESCRIPTION.rst
odoo10_addon_l10n_nl_account_tax_unece-10.0.1.0.0.dist-info/METADATA
odoo10_addon_l10n_nl_account_tax_unece-10.0.1.0.0.dist-info/RECORD
odoo10_addon_l10n_nl_account_tax_unece-10.0.1.0.0.dist-info/WHEEL
odoo10_addon_l10n_nl_account_tax_unece-10.0.1.0.0.dist-info/metadata.json
odoo10_addon_l10n_nl_account_tax_unece-10.0.1.0.0.dist-info/namespace_packages.txt
odoo10_addon_l10n_nl_account_tax_unece-10.0.1.0.0.dist-info/top_level.txt
